pysdccc/__init__.py
pysdccc/_cli.py
pysdccc/_common.py
pysdccc/_download.py
pysdccc/_result_parser.py
pysdccc/_runner.py
pysdccc/_runner_sync.py
pysdccc/py.typed
pysdccc-1.0.0.dist-info/METADATA
pysdccc-1.0.0.dist-info/WHEEL
pysdccc-1.0.0.dist-info/entry_points.txt
pysdccc-1.0.0.dist-info/licenses/LICENSE
pysdccc-1.0.0.dist-info/RECORD
