Metadata-Version: 2.4
Name: pysdccc
Version: 1.0.0
Summary: Python wrapper for SDCcc test tool
Project-URL: Homepage, https://github.com/Draegerwerk/pysdccc
Project-URL: Bug Tracker, https://github.com/Draegerwerk/pysdccc/issues
Project-URL: Changelog, https://github.com/Draegerwerk/pysdccc/blob/main/CHANGELOG.md
Project-URL: Repository, https://github.com/Draegerwerk/pysdccc.git
Author-email: Leon Budnick <leon.budnick@draeger.com>
License: MIT License
License-File: LICENSE
Keywords: SDCcc,sdc,test,wrapper
Classifier: Development Status :: 5 - Production/Stable
Classifier: License :: OSI Approved :: MIT License
Classifier: Operating System :: OS Independent
Classifier: Programming Language :: Python :: 3
Requires-Python: <3.14,>=3.11
Requires-Dist: anyio>=4.7.0
Requires-Dist: httpx>=0.28.0
Requires-Dist: junitparser>=4
Requires-Dist: typing-extensions>=4.13.2; python_version < '3.13'
Provides-Extra: cli
Requires-Dist: click>=8.0; extra == 'cli'
